README.md
setup.py
CaaS/__init__.py
CaaS/caas.py
CaaS/errors.py
CaaS/setup.py
CaaS.egg-info/PKG-INFO
CaaS.egg-info/SOURCES.txt
CaaS.egg-info/dependency_links.txt
CaaS.egg-info/top_level.txt