Metadata-Version: 2.1
Name: CaaS
Version: 1.1
Summary: A Python library for Compression as a Service. CaaS can compress images, audio, video, text files 
Home-page: https://github.com/MayurDeshmukh10/CaaS
Author: Mayur Deshmukh
Author-email: mayur.s.deshmukh10@gmail.com
License: MIT
Download-URL: https://github.com/MayurDeshmukh10/CaaS/archive/v_6.tar.gz
Keywords: compression,image compression,video compression,audio compression,text compression,Compression as a service
Platform: UNKNOWN
Classifier: Development Status :: 4 - Beta
Classifier: Intended Audience :: Developers
Classifier: Topic :: Software Development :: Build Tools
Classifier: License :: OSI Approved :: MIT License
Classifier: Programming Language :: Python :: 3
Classifier: Programming Language :: Python :: 3.4
Classifier: Programming Language :: Python :: 3.5
Classifier: Programming Language :: Python :: 3.6
